{
  "lookup": {
    "rules": {
      "[{\"prev_action\": {\"action_name\": \"action_listen\"}, \"user\": {\"intent\": \"goodbye_ml\"}}]": "utter_goodbye_ml",
      "[{\"prev_action\": {\"action_name\": \"action_listen\"}, \"user\": {\"intent\": \"goodbye_ml\"}}, {\"prev_action\": {\"action_name\": \"utter_goodbye_ml\"}, \"user\": {\"intent\": \"goodbye_ml\"}}]": "action_listen",
      "[{\"prev_action\": {\"action_name\": \"action_listen\"}, \"user\": {\"intent\": \"goodbye\"}}]": "utter_goodbye",
      "[{\"prev_action\": {\"action_name\": \"action_listen\"}, \"user\": {\"intent\": \"goodbye\"}}, {\"prev_action\": {\"action_name\": \"utter_goodbye\"}, \"user\": {\"intent\": \"goodbye\"}}]": "action_listen",
      "[{\"prev_action\": {\"action_name\": \"action_listen\"}, \"user\": {\"intent\": \"bot_challenge\"}}]": "utter_iamabot",
      "[{\"prev_action\": {\"action_name\": \"action_listen\"}, \"user\": {\"intent\": \"bot_challenge\"}}, {\"prev_action\": {\"action_name\": \"utter_iamabot\"}, \"user\": {\"intent\": \"bot_challenge\"}}]": "action_listen",
      "[{\"prev_action\": {\"action_name\": \"action_listen\"}, \"user\": {\"intent\": \"mood_great\"}}]": "utter_happy",
      "[{\"prev_action\": {\"action_name\": \"action_listen\"}, \"user\": {\"intent\": \"mood_great\"}}, {\"prev_action\": {\"action_name\": \"utter_happy\"}, \"user\": {\"intent\": \"mood_great\"}}]": "action_listen",
      "[{\"prev_action\": {\"action_name\": \"action_listen\"}, \"user\": {\"intent\": \"greet\"}}]": "utter_greet",
      "[{\"prev_action\": {\"action_name\": \"action_listen\"}, \"user\": {\"intent\": \"greet\"}}, {\"prev_action\": {\"action_name\": \"utter_greet\"}, \"user\": {\"intent\": \"greet\"}}]": "action_listen",
      "[{\"prev_action\": {\"action_name\": \"action_listen\"}, \"user\": {\"intent\": \"book_car\"}}]": "utter_book_car",
      "[{\"prev_action\": {\"action_name\": \"action_listen\"}, \"user\": {\"intent\": \"book_car\"}}, {\"prev_action\": {\"action_name\": \"utter_book_car\"}, \"user\": {\"intent\": \"book_car\"}}]": "action_listen",
      "[{\"prev_action\": {\"action_name\": \"action_listen\"}, \"user\": {\"intent\": \"book_car_ml\"}}]": "utter_book_car_ml",
      "[{\"prev_action\": {\"action_name\": \"action_listen\"}, \"user\": {\"intent\": \"book_car_ml\"}}, {\"prev_action\": {\"action_name\": \"utter_book_car_ml\"}, \"user\": {\"intent\": \"book_car_ml\"}}]": "action_listen",
      "[{\"prev_action\": {\"action_name\": \"action_listen\"}, \"user\": {\"intent\": \"greet_ml\"}}]": "utter_greet_ml",
      "[{\"prev_action\": {\"action_name\": \"action_listen\"}, \"user\": {\"intent\": \"greet_ml\"}}, {\"prev_action\": {\"action_name\": \"utter_greet_ml\"}, \"user\": {\"intent\": \"greet_ml\"}}]": "action_listen",
      "[{\"prev_action\": {\"action_name\": \"action_listen\"}, \"user\": {\"intent\": \"mood_unhappy_ml\"}}]": "utter_cheer_up_ml",
      "[{\"prev_action\": {\"action_name\": \"action_listen\"}, \"user\": {\"intent\": \"mood_unhappy_ml\"}}, {\"prev_action\": {\"action_name\": \"utter_cheer_up_ml\"}, \"user\": {\"intent\": \"mood_unhappy_ml\"}}]": "utter_did_that_help_ml",
      "[{\"prev_action\": {\"action_name\": \"action_listen\"}, \"user\": {\"intent\": \"mood_unhappy_ml\"}}, {\"prev_action\": {\"action_name\": \"utter_cheer_up_ml\"}, \"user\": {\"intent\": \"mood_unhappy_ml\"}}, {\"prev_action\": {\"action_name\": \"utter_did_that_help_ml\"}, \"user\": {\"intent\": \"mood_unhappy_ml\"}}]": "action_listen",
      "[{\"prev_action\": {\"action_name\": \"action_listen\"}, \"user\": {\"intent\": \"mood_great_ml\"}}]": "utter_happy_ml",
      "[{\"prev_action\": {\"action_name\": \"action_listen\"}, \"user\": {\"intent\": \"mood_great_ml\"}}, {\"prev_action\": {\"action_name\": \"utter_happy_ml\"}, \"user\": {\"intent\": \"mood_great_ml\"}}]": "action_listen",
      "[{\"prev_action\": {\"action_name\": \"action_listen\"}, \"user\": {\"intent\": \"mood_unhappy\"}}]": "utter_cheer_up",
      "[{\"prev_action\": {\"action_name\": \"action_listen\"}, \"user\": {\"intent\": \"mood_unhappy\"}}, {\"prev_action\": {\"action_name\": \"utter_cheer_up\"}, \"user\": {\"intent\": \"mood_unhappy\"}}]": "utter_did_that_help",
      "[{\"prev_action\": {\"action_name\": \"action_listen\"}, \"user\": {\"intent\": \"mood_unhappy\"}}, {\"prev_action\": {\"action_name\": \"utter_cheer_up\"}, \"user\": {\"intent\": \"mood_unhappy\"}}, {\"prev_action\": {\"action_name\": \"utter_did_that_help\"}, \"user\": {\"intent\": \"mood_unhappy\"}}]": "action_listen"
    },
    "rule_only_slots": [],
    "rule_only_loops": [],
    "rules_for_loop_unhappy_path": {},
    "rules_not_in_stories": [
      "[{\"prev_action\": {\"action_name\": \"action_listen\"}, \"user\": {\"intent\": \"bot_challenge\"}}, {\"prev_action\": {\"action_name\": \"utter_iamabot\"}, \"user\": {\"intent\": \"bot_challenge\"}}]",
      "predicting default action with intent back",
      "[{\"prev_action\": {\"action_name\": \"action_listen\"}, \"user\": {\"intent\": \"goodbye\"}}]",
      "[{\"prev_action\": {\"action_name\": \"action_listen\"}, \"user\": {\"intent\": \"goodbye\"}}, {\"prev_action\": {\"action_name\": \"utter_goodbye\"}, \"user\": {\"intent\": \"goodbye\"}}]",
      "[{\"prev_action\": {\"action_name\": \"action_listen\"}, \"user\": {\"intent\": \"goodbye_ml\"}}]",
      "predicting default action with intent restart",
      "predicting default action with intent session_start",
      "[{\"prev_action\": {\"action_name\": \"action_listen\"}, \"user\": {\"intent\": \"goodbye_ml\"}}, {\"prev_action\": {\"action_name\": \"utter_goodbye_ml\"}, \"user\": {\"intent\": \"goodbye_ml\"}}]",
      "[{\"prev_action\": {\"action_name\": \"action_listen\"}, \"user\": {\"intent\": \"bot_challenge\"}}]"
    ]
  }
}